{
  "versioniOS": "63.265",
  "versionANDROID": "63.286",
  "versionSERVER": "2.39.0",
  "date": "2025-09-12",
  "title": "Null's Brawl Update",

  "PREversioniOS": "63.265",
  "PREversionANDROID": "63.282",

  "newbrwlen": "Ziggy & Mina",
  "newbrwlru": "Зигги и Мина",

  "seasonBPen": "42 & 43",
  "seasonBPru": "42 и 43",

  "nameBPen": "Knights of the Starr Table",
  "nameBPru": "Легенды загробного мира и Рыцари круглого стола Старр",

  "minimalVios": "13",
  "minimalVandroid": "7",
  
  "sizeiOS": "901,7",
  "sizeAdnroid": "915,9",
   "_comment": "SIZE MB"
}
