{
  "versioniOS": "11.548.0",
  "versionANDROID": "11.548.0",
  "versionSERVER": "2.16.2",
  "date": "2025-08-20",
  "title": "text",
  "PREversionANDROID": "11.548.4",
  "PREversioniOSD": "11.548.4",

  "PREversioniOS": "63.265",
  "PREversionANDROID": "63.282",

  "newcarden": "Rework Furnace",
  "newbrwlru": "Измененная Печь",

  "emote": "490",
  "cards": "121",
  "towers": "121",
  "banner": "424",
  "bannerframe": "424",

  "season": "Goblins",
  "seasonru": "Гоблины",

  "minimalVios": "13",
  "minimalVandroid": "7",
  
  "sizeiOS": "849",
  "sizeAndroid": "880",
  
  "nr_youtube": "https://www.youtube.com/watch?v=45UB3Gfem7k",
  "nr_youtube2": "800"
}
